LICENSE
MANIFEST.in
README.md
setup.py
bin/iheartradio
iheartradio/__init__.py
iheartradio/iheartradio.py
iheartradio/rhythmbox.py
iheartradio.egg-info/PKG-INFO
iheartradio.egg-info/SOURCES.txt
iheartradio.egg-info/dependency_links.txt
iheartradio.egg-info/requires.txt
iheartradio.egg-info/top_level.txt