Metadata-Version: 2.1
Name: iheartradio
Version: 1.0.4
Summary: iheartradio radio station fetcher for rhythmbox
Home-page: https://github.com/hutchgrant/iheartradio-rhythmbox
Author: Grant Hutchinson(hutchgrant)
License: MIT
Platform: UNKNOWN
Classifier: Development Status :: 3 - Alpha
Classifier: License :: OSI Approved :: MIT License
Classifier: Programming Language :: Python :: 3.5
Classifier: Operating System :: POSIX :: Linux
Classifier: Topic :: Multimedia :: Sound/Audio
